{
  "students": [
    {
      "class": "Web02",
      "checked": false,
      "id": 1
    },
    {
      "name": "Nguyễn Hà Thu",
      "email": "nguyenlamson1609@gmail.com",
      "gender": "0",
      "address": "Cần Thơ",
      "class": "Web02",
      "checked": false,
      "id": 2
    },
    {
      "name": "Nguyễn Hải Ninh",
      "email": "sonyeuphuongdung@gmail.com",
      "gender": "1",
      "address": "Hải Phòng",
      "class": "Web12",
      "checked": false,
      "id": 3
    },
    {
      "name": "Nguyễn Thị Minh Nguyệt",
      "email": "nguyenthanhtra2k4@gmail.com",
      "gender": "0",
      "address": "Cần Thơ",
      "class": "Web02",
      "checked": false,
      "id": 4
    },
    {
      "name": "",
      "email": "gacon1999@gmail.com",
      "gender": "1",
      "address": "Hải Phòng",
      "class": "Web12",
      "checked": false,
      "id": 6
    }
  ]
}